snyk_mcp_server/__init__.py
snyk_mcp_server/main.py
snyk_mcp_server/snyk/__init__.py
snyk_mcp_server/snyk/client.py
snyk_mcp_server/snyk/models.py
snyk_mcp_server-0.1.0.dist-info/METADATA
snyk_mcp_server-0.1.0.dist-info/WHEEL
snyk_mcp_server-0.1.0.dist-info/entry_points.txt
snyk_mcp_server-0.1.0.dist-info/licenses/LICENSE
snyk_mcp_server-0.1.0.dist-info/RECORD
